unrartest/__init__.py
unrartest-0.0.1.dist-info/METADATA
unrartest-0.0.1.dist-info/WHEEL
unrartest-0.0.1.dist-info/entry_points.txt
unrartest-0.0.1.dist-info/top_level.txt
unrartest-0.0.1.dist-info/RECORD
