Metadata-Version: 2.1
Name: unrartest
Version: 0.0.1
Summary: The best python fast UnRar tool!
Home-page: https://github.com/unrartest
Author: superprodev
Author-email: superprodev@gmail.com
Classifier: Development Status :: 3 - Alpha
Classifier: Programming Language :: Python :: 3
Classifier: License :: OSI Approved :: MIT License
Classifier: Operating System :: OS Independent
